churchtools/__init__.py
churchtools/admin.py
churchtools/calendars.py
churchtools/departments.py
churchtools/events.py
churchtools/general.py
churchtools/group_homepages.py
churchtools/groups.py
churchtools/models/__init__.py
churchtools/models/admin.py
churchtools/models/calendar.py
churchtools/models/department.py
churchtools/models/event.py
churchtools/models/general.py
churchtools/models/group.py
churchtools/models/group_homepage.py
churchtools/models/pagination.py
churchtools/models/person.py
churchtools/models/resource.py
churchtools/models/service.py
churchtools/models/settings.py
churchtools/models/song.py
churchtools/models/status.py
churchtools/models/wiki.py
churchtools/persons.py
churchtools/resource.py
churchtools/services.py
churchtools/songs.py
churchtools/status.py
churchtools/wiki.py
churchtools-0.5.1.dist-info/LICENSE
churchtools-0.5.1.dist-info/METADATA
churchtools-0.5.1.dist-info/WHEEL
churchtools-0.5.1.dist-info/RECORD
