Metadata-Version: 2.3
Name: churchtools
Version: 0.5.1
Summary: A library for the ChurchTools API
License: GPLv3
Keywords: api,churchtools
Author: Philipp Glaum
Author-email: p@pglaum.de
Requires-Python: >=3.10,<4.0
Classifier: License :: OSI Approved :: GNU General Public License v3 (GPLv3)
Classifier: License :: Other/Proprietary License
Classifier: Operating System :: OS Independent
Classifier: Programming Language :: Python :: 3
Classifier: Programming Language :: Python :: 3.10
Classifier: Programming Language :: Python :: 3.11
Classifier: Programming Language :: Python :: 3.12
Classifier: Programming Language :: Python :: 3.13
Requires-Dist: pydantic (>=2.10.6,<3.0.0)
Requires-Dist: requests (>=2.32.3,<3.0.0)
Project-URL: Homepage, https://github.com/pglaum/pychurchtools
Project-URL: Issues, https://github.com/pglaum/pychurchtools/issues
